setup.cfg
setup.py
scrapyd_mongodb/__init__.py
scrapyd_mongodb/application.py
scrapyd_mongodb/launcher.py
scrapyd_mongodb/mongodb.py
scrapyd_mongodb/poller.py
scrapyd_mongodb/scheduler.py
scrapyd_mongodb/spiderqueue.py
scrapyd_mongodb/utils.py
scrapyd_mongodb.egg-info/PKG-INFO
scrapyd_mongodb.egg-info/SOURCES.txt
scrapyd_mongodb.egg-info/dependency_links.txt
scrapyd_mongodb.egg-info/requires.txt
scrapyd_mongodb.egg-info/top_level.txt