Metadata-Version: 1.1
Name: scrapyd-mongodb
Version: 0.1.1
Summary: Scrapyd Queue Management with MongoDB
Home-page: https://github.com/Tiago-Lira/scrapyd-mongodb
Author: Tiago Lira
Author-email: tiagolira.dev@gmail.com
License: MIT
Download-URL: https://github.com/Tiago-Lira/scrapyd-mongodb/tarball/0.1.1
Keywords: scrapy,scrapyd,mongodb,queue,scrapyd-queue,scrapyd-backend,backend
Platform: UNKNOWN
